[
  {
    "outageRecId": "2021-09-10-0023",
    "points": {},
    "outNow": 1
  },
  {
    "outageRecId": "2021-09-11-0025",
    "points": {
      "type": "Polygon",
      "coordinates": [
        [
          [
            -87.02955086396985,
            35.60613390937396
          ],
          [
            -87.02995784933525,
            35.60618945663426
          ],
          [
            -87.03033510372343,
            35.60625503243665
          ],
          [
            -87.03122690186383,
            35.60708062735139
          ],
          [
            -87.03145946222722,
            35.60739454850457
          ],
          [
            -87.03087597978379,
            35.60827752860407
          ],
          [
            -87.02940410138463,
            35.60732740345547
          ],
          [
            -87.02823606073518,
            35.60761200950997
          ],
          [
            -87.02652863532792,
            35.60720305321282
          ],
          [
            -87.02567191361032,
            35.60734428400855
          ],
          [
            -87.02535823596295,
            35.60705970270571
          ],
          [
            -87.02529048886194,
            35.60665859843147
          ],
          [
            -87.02605755379689,
            35.60487488398436
          ],
          [
            -87.02612511955972,
            35.6045651307364
          ],
          [
            -87.026199353127,
            35.6045425846669
          ],
          [
            -87.02766799694189,
            35.60470041053723
          ],
          [
            -87.02782389541544,
            35.60476967243842
          ],
          [
            -87.02936693567668,
            35.60611628040265
          ],
          [
            -87.02955086396985,
            35.60613390937396
          ]
        ]
      ]
    },
    "outNow": 96
  },
  {
    "outageRecId": "2021-09-11-0031",
    "points": {},
    "outNow": 1
  },
  {
    "outageRecId": "2021-09-11-0032",
    "points": {
      "type": "Polygon",
      "coordinates": [
        [
          [
            -87.01950644314024,
            35.60085786410672
          ],
          [
            -87.01951051760572,
            35.60086301303943
          ],
          [
            -87.01951425362886,
            35.60086789195648
          ],
          [
            -87.0195190197827,
            35.6008749438624
          ],
          [
            -87.01897563634128,
            35.60113889210433
          ],
          [
            -87.0188587992286,
            35.60119735390764
          ],
          [
            -87.0188519670471,
            35.60118901133476
          ],
          [
            -87.01884995618904,
            35.60118644436987
          ],
          [
            -87.01884834142315,
            35.6011838733338
          ],
          [
            -87.0188463223179,
            35.60118065936836
          ],
          [
            -87.01885834580654,
            35.60114641466557
          ],
          [
            -87.01950644314024,
            35.60085786410672
          ]
        ]
      ]
    },
    "outNow": 25
  },
  {
    "outageRecId": "2021-09-11-0033",
    "points": {
      "type": "Polygon",
      "coordinates": [
        [
          [
            -87.02281924093401,
            35.59162580727553
          ],
          [
            -87.02335178055375,
            35.59169912318318
          ],
          [
            -87.02344748417207,
            35.59170871424977
          ],
          [
            -87.02370863015612,
            35.59174609598161
          ],
          [
            -87.02415767912855,
            35.5917818704034
          ],
          [
            -87.02531894723417,
            35.59127406078827
          ],
          [
            -87.0254137393878,
            35.59128899009381
          ],
          [
            -87.0254716914793,
            35.59129994163935
          ],
          [
            -87.02588837985832,
            35.59138889642473
          ],
          [
            -87.02670321257837,
            35.59209701751153
          ],
          [
            -87.02730857410239,
            35.59259530616817
          ],
          [
            -87.02712956887073,
            35.5926056159755
          ],
          [
            -87.02607849430775,
            35.59242398824328
          ],
          [
            -87.02518581425035,
            35.59230288993908
          ],
          [
            -87.02434181915179,
            35.59219622400186
          ],
          [
            -87.02328911366742,
            35.59207602597951
          ],
          [
            -87.02276666781086,
            35.59203637700442
          ],
          [
            -87.02281924093401,
            35.59162580727553
          ]
        ]
      ]
    },
    "outNow": 52
  },
  {
    "outageRecId": "2021-09-11-0035",
    "points": {
      "type": "Polygon",
      "coordinates": [
        [
          [
            -86.99520495463356,
            35.63850595170729
          ],
          [
            -86.99547290284407,
            35.63884084312529
          ],
          [
            -86.9959444060731,
            35.63948552687022
          ],
          [
            -86.9972718637493,
            35.64089904680678
          ],
          [
            -86.99726947353577,
            35.64118236437637
          ],
          [
            -86.99684437024631,
            35.64321306675804
          ],
          [
            -86.9962398050586,
            35.64558876467138
          ],
          [
            -86.99619498058854,
            35.64654419193357
          ],
          [
            -86.99603534475531,
            35.64725477222371
          ],
          [
            -86.99543298311023,
            35.64733698398721
          ],
          [
            -86.9942903340724,
            35.64677307168684
          ],
          [
            -86.9932156461205,
            35.64596219885634
          ],
          [
            -86.99204118948632,
            35.64398346135854
          ],
          [
            -86.99168972572237,
            35.64384122578187
          ],
          [
            -86.99107211316341,
            35.64374473217967
          ],
          [
            -86.9905034239566,
            35.64373007963568
          ],
          [
            -86.99027736810915,
            35.64370291837165
          ],
          [
            -86.98944644586258,
            35.64362982879581
          ],
          [
            -86.98818191758816,
            35.64344443626915
          ],
          [
            -86.98873164392793,
            35.64180989166057
          ],
          [
            -86.98883495569855,
            35.64161508651064
          ],
          [
            -86.9891962768944,
            35.64111861883739
          ],
          [
            -86.98940309699196,
            35.64106853134202
          ],
          [
            -86.98997141884564,
            35.64101545893948
          ],
          [
            -86.9913820474618,
            35.64101831637834
          ],
          [
            -86.99305457036058,
            35.63937097428853
          ],
          [
            -86.99285258252829,
            35.63872799120114
          ],
          [
            -86.99520495463356,
            35.63850595170729
          ]
        ]
      ]
    },
    "outNow": 161
  },
  {
    "outageRecId": "2021-09-11-0036",
    "points": {},
    "outNow": 1
  },
  {
    "outageRecId": "2021-09-11-0040",
    "points": {
      "type": "Polygon",
      "coordinates": [
        [
          [
            -87.00594903038231,
            35.58949115496092
          ],
          [
            -87.00733963379805,
            35.58954961159931
          ],
          [
            -87.00685021772335,
            35.59047217825579
          ],
          [
            -87.00451141272428,
            35.59108728897385
          ],
          [
            -87.0039904475505,
            35.59096511683179
          ],
          [
            -87.00150521729805,
            35.59044254156433
          ],
          [
            -87.00594903038231,
            35.58949115496092
          ]
        ]
      ]
    },
    "outNow": 14
  },
  {
    "outageRecId": "2021-09-11-0041",
    "points": {},
    "outNow": 1
  },
  {
    "outageRecId": "2021-09-11-0044",
    "points": {
      "type": "Polygon",
      "coordinates": [
        [
          [
            -87.03815530094403,
            35.60390963814902
          ],
          [
            -87.0382475772994,
            35.60374927657242
          ],
          [
            -87.0382685960541,
            35.60375398477432
          ],
          [
            -87.03849759351473,
            35.6043370600801
          ],
          [
            -87.03793950192787,
            35.60481375555118
          ],
          [
            -87.0374572163106,
            35.60463404681313
          ],
          [
            -87.03704205514558,
            35.60470321265365
          ],
          [
            -87.03747898302207,
            35.60424454977114
          ],
          [
            -87.03815530094403,
            35.60390963814902
          ]
        ]
      ]
    },
    "outNow": 13
  },
  {
    "outageRecId": "2021-09-11-0045",
    "points": {
      "type": "Polygon",
      "coordinates": [
        [
          [
            -87.01687088134196,
            35.60264294741448
          ],
          [
            -87.01686202650887,
            35.60263265887948
          ],
          [
            -87.01788268466454,
            35.60311797887558
          ],
          [
            -87.01788518275956,
            35.60312046083379
          ],
          [
            -87.01788133469712,
            35.60312254093593
          ],
          [
            -87.01787220355011,
            35.60312668097588
          ],
          [
            -87.01786690360652,
            35.60312897245475
          ],
          [
            -87.01732716443084,
            35.60312526707871
          ],
          [
            -87.01687088134196,
            35.60264294741448
          ]
        ]
      ]
    },
    "outNow": 23
  },
  {
    "outageRecId": "2021-09-11-0046",
    "points": {
      "type": "Polygon",
      "coordinates": [
        [
          [
            -87.0167076769373,
            35.60871395698315
          ],
          [
            -87.01843553141634,
            35.6081810870794
          ],
          [
            -87.01919650979175,
            35.60902698129603
          ],
          [
            -87.0189717593546,
            35.61000475162614
          ],
          [
            -87.01689988710216,
            35.61049047774617
          ],
          [
            -87.01669303755688,
            35.60872861001398
          ],
          [
            -87.0167076769373,
            35.60871395698315
          ]
        ]
      ]
    },
    "outNow": 8
  },
  {
    "outageRecId": "2021-09-11-0050",
    "points": {},
    "outNow": 1
  },
  {
    "outageRecId": "2021-09-11-0051",
    "points": {
      "type": "Polygon",
      "coordinates": [
        [
          [
            -87.0321559504522,
            35.59757617273734
          ],
          [
            -87.03260884086514,
            35.59764740622939
          ],
          [
            -87.03257306324392,
            35.59781922093052
          ],
          [
            -87.03362215187445,
            35.59899111561784
          ],
          [
            -87.03380667176185,
            35.59903199208238
          ],
          [
            -87.03410332211028,
            35.5990833340884
          ],
          [
            -87.03433734809553,
            35.59908621433601
          ],
          [
            -87.03466900779405,
            35.59921565533771
          ],
          [
            -87.03441889276543,
            35.59990324495212
          ],
          [
            -87.03345326526878,
            35.60031398427247
          ],
          [
            -87.03335663916549,
            35.60011064396893
          ],
          [
            -87.03219991912472,
            35.59912261333125
          ],
          [
            -87.03156843850223,
            35.5990055473977
          ],
          [
            -87.03121207366117,
            35.59897594685006
          ],
          [
            -87.03055790423967,
            35.59896034038758
          ],
          [
            -87.03011490184724,
            35.59841533168601
          ],
          [
            -87.03045995884082,
            35.59818859050189
          ],
          [
            -87.0310078628005,
            35.59787353333408
          ],
          [
            -87.03144702497009,
            35.59765577981234
          ],
          [
            -87.03161400444809,
            35.59757757287422
          ],
          [
            -87.03188559804775,
            35.59754746714796
          ],
          [
            -87.0321559504522,
            35.59757617273734
          ]
        ]
      ]
    },
    "outNow": 82
  },
  {
    "outageRecId": "2021-09-11-0052",
    "points": {
      "type": "Polygon",
      "coordinates": [
        [
          [
            -87.03719798498365,
            35.60161370669585
          ],
          [
            -87.03765535683466,
            35.60149023064148
          ],
          [
            -87.0379723427342,
            35.60148386376997
          ],
          [
            -87.0381364131471,
            35.60182469427043
          ],
          [
            -87.03798255494848,
            35.6020994670595
          ],
          [
            -87.03755134118511,
            35.6020845296792
          ],
          [
            -87.03729333909558,
            35.60212716558214
          ],
          [
            -87.03719798498365,
            35.60161370669585
          ]
        ]
      ]
    },
    "outNow": 15
  },
  {
    "outageRecId": "2021-09-11-0053",
    "points": {},
    "outNow": 1
  },
  {
    "outageRecId": "2021-09-11-0055",
    "points": {},
    "outNow": 1
  },
  {
    "outageRecId": "2021-09-11-0056",
    "points": {},
    "outNow": 1
  },
  {
    "outageRecId": "2021-09-11-0057",
    "points": {},
    "outNow": 1
  },
  {
    "outageRecId": "2021-09-11-0058",
    "points": {},
    "outNow": 1
  },
  {
    "outageRecId": "2021-09-11-0059",
    "points": {},
    "outNow": 1
  },
  {
    "outageRecId": "2021-09-11-0062",
    "points": {},
    "outNow": 1
  },
  {
    "outageRecId": "2021-09-11-0063",
    "points": {
      "type": "Polygon",
      "coordinates": [
        [
          [
            -86.97270316090712,
            35.62203755783861
          ],
          [
            -86.97390236813536,
            35.62052603726169
          ],
          [
            -86.97473418412879,
            35.62033251798395
          ],
          [
            -86.97852833763199,
            35.62033255075636
          ],
          [
            -86.98260254269353,
            35.62122403032714
          ],
          [
            -86.98473490332096,
            35.62502957169969
          ],
          [
            -86.98598584340426,
            35.62499731598892
          ],
          [
            -86.98652847409942,
            35.62535538091846
          ],
          [
            -86.98672587390037,
            35.62786202495604
          ],
          [
            -86.98488455074052,
            35.62770682712683
          ],
          [
            -86.98164396807975,
            35.62615037870004
          ],
          [
            -86.97868993622578,
            35.62583709713349
          ],
          [
            -86.97427626890023,
            35.62631668304722
          ],
          [
            -86.97270316090712,
            35.62203755783861
          ]
        ]
      ]
    },
    "outNow": 54
  },
  {
    "outageRecId": "2021-09-11-0065",
    "points": {},
    "outNow": 1
  },
  {
    "outageRecId": "2021-09-11-0066",
    "points": {},
    "outNow": 1
  },
  {
    "outageRecId": "2021-09-11-0067",
    "points": {},
    "outNow": 1
  },
  {
    "outageRecId": "2021-09-11-0074",
    "points": {
      "type": "Polygon",
      "coordinates": [
        [
          [
            -87.02523635682608,
            35.60731879727667
          ],
          [
            -87.02525129120171,
            35.60732110446303
          ],
          [
            -87.02565247289104,
            35.60768770734184
          ],
          [
            -87.02558400976608,
            35.60769559673766
          ],
          [
            -87.02505459814672,
            35.60779020139821
          ],
          [
            -87.02523635682608,
            35.60731879727667
          ]
        ]
      ]
    },
    "outNow": 7
  },
  {
    "outageRecId": "2021-09-11-0081",
    "points": {},
    "outNow": 1
  },
  {
    "outageRecId": "2021-09-11-0082",
    "points": {},
    "outNow": 1
  },
  {
    "outageRecId": "2021-09-11-0083",
    "points": {},
    "outNow": 1
  },
  {
    "outageRecId": "2021-09-11-0084",
    "points": {},
    "outNow": 1
  },
  {
    "outageRecId": "2021-09-11-0085",
    "points": {},
    "outNow": 1
  },
  {
    "outageRecId": "2021-09-11-0087",
    "points": {
      "type": "Polygon",
      "coordinates": [
        [
          [
            -87.03241198055605,
            35.60024578166718
          ],
          [
            -87.03290643566979,
            35.6002484631097
          ],
          [
            -87.03318846864138,
            35.60026535815468
          ],
          [
            -87.03322372768328,
            35.60029850070415
          ],
          [
            -87.03282266985718,
            35.60057586278611
          ],
          [
            -87.03290187228819,
            35.60097862714115
          ],
          [
            -87.0327531957366,
            35.60092600686418
          ],
          [
            -87.03232126685946,
            35.60062101863567
          ],
          [
            -87.03213897635189,
            35.60059808815202
          ],
          [
            -87.0321882075809,
            35.60027088676847
          ],
          [
            -87.03241198055605,
            35.60024578166718
          ]
        ]
      ]
    },
    "outNow": 16
  },
  {
    "outageRecId": "2021-09-11-0090",
    "points": {},
    "outNow": 1
  },
  {
    "outageRecId": "2021-09-11-0091",
    "points": {},
    "outNow": 1
  },
  {
    "outageRecId": "2021-09-11-0093",
    "points": {},
    "outNow": 1
  },
  {
    "outageRecId": "2021-09-11-0107",
    "points": {
      "type": "Polygon",
      "coordinates": [
        [
          [
            -87.0198740178376,
            35.61604999753635
          ],
          [
            -87.02060561164625,
            35.61612106573893
          ],
          [
            -87.02125659265938,
            35.61622114401738
          ],
          [
            -87.02082244308713,
            35.61651371573149
          ],
          [
            -87.02088029956867,
            35.6173091616534
          ],
          [
            -87.02068754805136,
            35.61692135314759
          ],
          [
            -87.0199125290146,
            35.61645574265757
          ],
          [
            -87.0198740178376,
            35.61604999753635
          ]
        ]
      ]
    },
    "outNow": 14
  },
  {
    "outageRecId": "2021-09-11-0118",
    "points": {
      "type": "Polygon",
      "coordinates": [
        [
          [
            -87.02981959967924,
            35.60110768638518
          ],
          [
            -87.02978257535139,
            35.60093527519395
          ],
          [
            -87.03014465266189,
            35.60077911159976
          ],
          [
            -87.03007784356846,
            35.60120385672692
          ],
          [
            -87.03057448244742,
            35.60120614574986
          ],
          [
            -87.03037970811864,
            35.60156858486723
          ],
          [
            -87.03026716774512,
            35.60156080651618
          ],
          [
            -87.03008962187901,
            35.60128684085124
          ],
          [
            -87.02981959967924,
            35.60110768638518
          ]
        ]
      ]
    },
    "outNow": 8
  },
  {
    "outageRecId": "2021-09-11-0120",
    "points": {},
    "outNow": 1
  },
  {
    "outageRecId": "2021-09-11-0121",
    "points": {},
    "outNow": 1
  },
  {
    "outageRecId": "2021-09-11-0122",
    "points": {
      "type": "Polygon",
      "coordinates": [
        [
          [
            -87.02651730743435,
            35.59808155251847
          ],
          [
            -87.02646398845152,
            35.59768188919476
          ],
          [
            -87.02739470171721,
            35.59761269186244
          ],
          [
            -87.02766860042236,
            35.5978415722734
          ],
          [
            -87.02793322313855,
            35.59840648375223
          ],
          [
            -87.02744261561593,
            35.59884106541004
          ],
          [
            -87.02726992601295,
            35.59873541000464
          ],
          [
            -87.02651730743435,
            35.59808155251847
          ]
        ]
      ]
    },
    "outNow": 9
  },
  {
    "outageRecId": "2021-09-11-0123",
    "points": {},
    "outNow": 1
  },
  {
    "outageRecId": "2021-09-11-0124",
    "points": {},
    "outNow": 1
  },
  {
    "outageRecId": "2021-09-11-0126",
    "points": {},
    "outNow": 1
  },
  {
    "outageRecId": "2021-09-11-0127",
    "points": {},
    "outNow": 1
  },
  {
    "outageRecId": "2021-09-11-0139",
    "points": {},
    "outNow": 1
  },
  {
    "outageRecId": "2021-09-11-0140",
    "points": {},
    "outNow": 1
  },
  {
    "outageRecId": "2021-09-11-0153",
    "points": {
      "type": "Polygon",
      "coordinates": [
        [
          [
            -87.03534425979355,
            35.60373407601363
          ],
          [
            -87.03534437641156,
            35.60374307844495
          ],
          [
            -87.03519873052366,
            35.60433455676228
          ],
          [
            -87.0349482002136,
            35.60538262466941
          ],
          [
            -87.03505635820869,
            35.60485611440973
          ],
          [
            -87.03487583598675,
            35.6039546535444
          ],
          [
            -87.03534425979355,
            35.60373407601363
          ]
        ]
      ]
    },
    "outNow": 14
  },
  {
    "outageRecId": "2021-09-11-0154",
    "points": {},
    "outNow": 1
  },
  {
    "outageRecId": "2021-09-11-0155",
    "points": {},
    "outNow": 1
  },
  {
    "outageRecId": "2021-09-11-0179",
    "points": {
      "type": "Polygon",
      "coordinates": [
        [
          [
            -86.95584662534709,
            35.57679202140557
          ],
          [
            -86.9635273079255,
            35.57575506131227
          ],
          [
            -86.95558954843466,
            35.58809783805136
          ],
          [
            -86.95751970322678,
            35.59398466614255
          ],
          [
            -86.9538344446154,
            35.59849624421207
          ],
          [
            -86.94955677319898,
            35.59855245545544
          ],
          [
            -86.9364547265647,
            35.59956419734167
          ],
          [
            -86.93601121377495,
            35.59850767508532
          ],
          [
            -86.93567625405302,
            35.59678321297719
          ],
          [
            -86.93831745550474,
            35.5958447280914
          ],
          [
            -86.94544291493393,
            35.59409497933058
          ],
          [
            -86.95350616273682,
            35.58786958120504
          ],
          [
            -86.95477897168222,
            35.58254242821669
          ],
          [
            -86.95416343402047,
            35.57784344714481
          ],
          [
            -86.95584662534709,
            35.57679202140557
          ]
        ]
      ]
    },
    "outNow": 63
  },
  {
    "outageRecId": "2021-09-11-0185",
    "points": {
      "type": "Polygon",
      "coordinates": [
        [
          [
            -87.04814495721382,
            35.61225983335006
          ],
          [
            -87.04825858418192,
            35.61223594917625
          ],
          [
            -87.04838127277223,
            35.6126560187297
          ],
          [
            -87.04815832133406,
            35.61283070472497
          ],
          [
            -87.04788262255501,
            35.61480838410596
          ],
          [
            -87.04774809708002,
            35.61485594263432
          ],
          [
            -87.04727426531359,
            35.61501842535734
          ],
          [
            -87.04693486342327,
            35.61497660769982
          ],
          [
            -87.0457010113526,
            35.61337892406545
          ],
          [
            -87.04532754821533,
            35.61339579592599
          ],
          [
            -87.04515363185222,
            35.61328257146205
          ],
          [
            -87.04551293771598,
            35.61296942540205
          ],
          [
            -87.04662253648935,
            35.61296408267377
          ],
          [
            -87.04771233151179,
            35.6124267557764
          ],
          [
            -87.04771816473782,
            35.61242350599443
          ],
          [
            -87.04814495721382,
            35.61225983335006
          ]
        ]
      ]
    },
    "outNow": 40
  },
  {
    "outageRecId": "2021-09-11-0186",
    "points": {
      "type": "Polygon",
      "coordinates": [
        [
          [
            -87.04224281892695,
            35.6043033086
          ],
          [
            -87.04275806114617,
            35.60427448498719
          ],
          [
            -87.04307614983473,
            35.6046684709849
          ],
          [
            -87.04230109469104,
            35.60465817581593
          ],
          [
            -87.04207729994783,
            35.60463821596928
          ],
          [
            -87.04163814346056,
            35.60455927572352
          ],
          [
            -87.04088296768983,
            35.60447334296712
          ],
          [
            -87.04076950133366,
            35.6044572901126
          ],
          [
            -87.04041651669543,
            35.60435812430942
          ],
          [
            -87.03979370439927,
            35.60436596368261
          ],
          [
            -87.03963842125044,
            35.60434297053571
          ],
          [
            -87.0393573095926,
            35.60426995275862
          ],
          [
            -87.03999850905228,
            35.60430090065556
          ],
          [
            -87.04039163247641,
            35.60404921299108
          ],
          [
            -87.04088372928699,
            35.6040741485074
          ],
          [
            -87.04171644736158,
            35.60416427497714
          ],
          [
            -87.04190149979863,
            35.60418457304883
          ],
          [
            -87.04224281892695,
            35.6043033086
          ]
        ]
      ]
    },
    "outNow": 32
  },
  {
    "outageRecId": "2021-09-11-0187",
    "points": {
      "type": "Polygon",
      "coordinates": [
        [
          [
            -87.04142617880592,
            35.6110985152561
          ],
          [
            -87.04142024977052,
            35.61112517496034
          ],
          [
            -87.04141772346901,
            35.61113649991782
          ],
          [
            -87.04101661420512,
            35.61145021573696
          ],
          [
            -87.04054343219363,
            35.61128191220495
          ],
          [
            -87.04142617880592,
            35.6110985152561
          ]
        ]
      ]
    },
    "outNow": 11
  },
  {
    "outageRecId": "2021-09-11-0188",
    "points": {},
    "outNow": 1
  },
  {
    "outageRecId": "2021-09-11-0189",
    "points": {},
    "outNow": 1
  },
  {
    "outageRecId": "2021-09-11-0190",
    "points": {},
    "outNow": 1
  },
  {
    "outageRecId": "2021-09-11-0191",
    "points": {},
    "outNow": 1
  },
  {
    "outageRecId": "2021-09-11-0192",
    "points": {},
    "outNow": 1
  },
  {
    "outageRecId": "2021-09-11-0193",
    "points": {
      "type": "Polygon",
      "coordinates": [
        [
          [
            -87.03874740307307,
            35.60424164428923
          ],
          [
            -87.03923001422474,
            35.60456557927147
          ],
          [
            -87.03886061812425,
            35.60531769609772
          ],
          [
            -87.03832546921404,
            35.60553537695516
          ],
          [
            -87.03806064567773,
            35.60536588429569
          ],
          [
            -87.0383217920051,
            35.60479830267296
          ],
          [
            -87.03874740307307,
            35.60424164428923
          ]
        ]
      ]
    },
    "outNow": 14
  },
  {
    "outageRecId": "2021-09-11-0194",
    "points": {},
    "outNow": 1
  },
  {
    "outageRecId": "2021-09-11-0195",
    "points": {},
    "outNow": 1
  },
  {
    "outageRecId": "2021-09-11-0196",
    "points": {},
    "outNow": 1
  },
  {
    "outageRecId": "2021-09-11-0197",
    "points": {},
    "outNow": 1
  },
  {
    "outageRecId": "2021-09-11-0198",
    "points": {},
    "outNow": 1
  },
  {
    "outageRecId": "2021-09-11-0199",
    "points": {},
    "outNow": 1
  },
  {
    "outageRecId": "2021-09-11-0200",
    "points": {},
    "outNow": 1
  },
  {
    "outageRecId": "2021-09-11-0201",
    "points": {},
    "outNow": 1
  },
  {
    "outageRecId": "2021-09-11-0202",
    "points": {},
    "outNow": 1
  },
  {
    "outageRecId": "2021-09-11-0203",
    "points": {},
    "outNow": 1
  },
  {
    "outageRecId": "2021-09-11-0204",
    "points": {},
    "outNow": 1
  },
  {
    "outageRecId": "2021-09-11-0205",
    "points": {},
    "outNow": 1
  },
  {
    "outageRecId": "2021-09-11-0206",
    "points": {},
    "outNow": 1
  },
  {
    "outageRecId": "2021-09-11-0207",
    "points": {},
    "outNow": 1
  },
  {
    "outageRecId": "2021-09-11-0208",
    "points": {
      "type": "Polygon",
      "coordinates": [
        [
          [
            -87.0427764451913,
            35.60645556370909
          ],
          [
            -87.04310947413175,
            35.60618909102656
          ],
          [
            -87.04354594585948,
            35.60653275917195
          ],
          [
            -87.04297490552848,
            35.60674887552762
          ],
          [
            -87.04269689063003,
            35.60678272801353
          ],
          [
            -87.04253616928094,
            35.60679493385953
          ],
          [
            -87.04247142208533,
            35.60652279569013
          ],
          [
            -87.0427764451913,
            35.60645556370909
          ]
        ]
      ]
    },
    "outNow": 10
  },
  {
    "outageRecId": "2021-09-11-0209",
    "points": {},
    "outNow": 1
  },
  {
    "outageRecId": "2021-09-11-0210",
    "points": {},
    "outNow": 1
  },
  {
    "outageRecId": "2021-09-11-0211",
    "points": {},
    "outNow": 1
  },
  {
    "outageRecId": "2021-09-11-0212",
    "points": {
      "type": "Polygon",
      "coordinates": [
        [
          [
            -87.01925973420472,
            35.60152222775731
          ],
          [
            -87.01926214184094,
            35.6015252478065
          ],
          [
            -87.01926695975946,
            35.6015315628873
          ],
          [
            -87.01915302536158,
            35.60158269823008
          ],
          [
            -87.01915084089347,
            35.60157995761571
          ],
          [
            -87.01914646790429,
            35.60157422603309
          ],
          [
            -87.01914209491572,
            35.60156849445027
          ],
          [
            -87.01913615548261,
            35.60156026808788
          ],
          [
            -87.01924975995225,
            35.60150959977009
          ],
          [
            -87.01925732657759,
            35.60151920841128
          ],
          [
            -87.01925973420472,
            35.60152222775731
          ]
        ]
      ]
    },
    "outNow": 17
  },
  {
    "outageRecId": "2021-09-11-0216",
    "points": {},
    "outNow": 1
  },
  {
    "outageRecId": "2021-09-11-0218",
    "points": {},
    "outNow": 1
  },
  {
    "outageRecId": "2021-09-11-0219",
    "points": {},
    "outNow": 1
  },
  {
    "outageRecId": "2021-09-11-0220",
    "points": {},
    "outNow": 1
  },
  {
    "outageRecId": "2021-09-11-0221",
    "points": {
      "type": "Polygon",
      "coordinates": [
        [
          [
            -86.9745918009863,
            35.62761422053854
          ],
          [
            -86.97683665021955,
            35.62793288355491
          ],
          [
            -86.97708370757172,
            35.62847051023406
          ],
          [
            -86.97854064684196,
            35.63046530330109
          ],
          [
            -86.9809564033985,
            35.63156763741449
          ],
          [
            -86.98177334061968,
            35.63191220857775
          ],
          [
            -86.98213461303652,
            35.63204608417323
          ],
          [
            -86.98200855228114,
            35.63257377230568
          ],
          [
            -86.98120811003535,
            35.63259984076259
          ],
          [
            -86.9784527682439,
            35.63474938372296
          ],
          [
            -86.97721648626224,
            35.63506198992284
          ],
          [
            -86.9753832415542,
            35.63468663184273
          ],
          [
            -86.97469420080238,
            35.63440904359563
          ],
          [
            -86.97383760239862,
            35.63131948035614
          ],
          [
            -86.97361685554323,
            35.62875674485038
          ],
          [
            -86.9745918009863,
            35.62761422053854
          ]
        ]
      ]
    },
    "outNow": 54
  },
  {
    "outageRecId": "2021-09-11-0222",
    "points": {
      "type": "Polygon",
      "coordinates": [
        [
          [
            -86.9534893147345,
            35.61738120151994
          ],
          [
            -86.95432320792187,
            35.61727428068728
          ],
          [
            -86.95877111561359,
            35.61645501676107
          ],
          [
            -86.96151396921873,
            35.61694997757435
          ],
          [
            -86.96165040528248,
            35.61723345139374
          ],
          [
            -86.96167261422228,
            35.62213257086467
          ],
          [
            -86.96160538910298,
            35.62301655076149
          ],
          [
            -86.96068836291491,
            35.62310898632041
          ],
          [
            -86.9585380870583,
            35.62740975883746
          ],
          [
            -86.95906194669152,
            35.62810225423223
          ],
          [
            -86.95919990874393,
            35.62972191274557
          ],
          [
            -86.95666855621973,
            35.63334443426608
          ],
          [
            -86.95665665341373,
            35.63335227714795
          ],
          [
            -86.95185947075731,
            35.63169586878553
          ],
          [
            -86.95158295737481,
            35.63154770451546
          ],
          [
            -86.94827432499865,
            35.63032433962384
          ],
          [
            -86.94605252906905,
            35.63021080956429
          ],
          [
            -86.94262070141266,
            35.63113186782426
          ],
          [
            -86.93992537521419,
            35.63013164856963
          ],
          [
            -86.94256295155273,
            35.62907258311322
          ],
          [
            -86.94592032372908,
            35.62932311565746
          ],
          [
            -86.94928766643652,
            35.62539815575604
          ],
          [
            -86.95039698394,
            35.62145178494471
          ],
          [
            -86.95052800574238,
            35.62042611335657
          ],
          [
            -86.9534893147345,
            35.61738120151994
          ]
        ]
      ]
    },
    "outNow": 212
  },
  {
    "outageRecId": "2021-09-11-0223",
    "points": {
      "type": "Polygon",
      "coordinates": [
        [
          [
            -86.94789650696558,
            35.61029505866101
          ],
          [
            -86.95190972123729,
            35.60968404199086
          ],
          [
            -86.95130846352671,
            35.61340188393952
          ],
          [
            -86.95103320189509,
            35.61428532184601
          ],
          [
            -86.95035047021139,
            35.62241891526414
          ],
          [
            -86.95030436728304,
            35.62300154213905
          ],
          [
            -86.94994990311936,
            35.62378182400778
          ],
          [
            -86.94875070803933,
            35.62390512382534
          ],
          [
            -86.94769880345969,
            35.62383351042359
          ],
          [
            -86.94668736805806,
            35.62348832202702
          ],
          [
            -86.94577823810822,
            35.6227746229015
          ],
          [
            -86.94541344086853,
            35.62249205330304
          ],
          [
            -86.94473144009329,
            35.62121035934438
          ],
          [
            -86.94478750191448,
            35.62067017267413
          ],
          [
            -86.94479980884752,
            35.62052485751336
          ],
          [
            -86.94488552443656,
            35.62006505930047
          ],
          [
            -86.94299100903707,
            35.61343861817392
          ],
          [
            -86.93959921581761,
            35.61162519093438
          ],
          [
            -86.93687609605873,
            35.60872716402413
          ],
          [
            -86.93926700512655,
            35.60552899188421
          ],
          [
            -86.94345456977447,
            35.60628236155355
          ],
          [
            -86.94789650696558,
            35.61029505866101
          ]
        ]
      ]
    },
    "outNow": 92
  },
  {
    "outageRecId": "2021-09-11-0224",
    "points": {
      "type": "Polygon",
      "coordinates": [
        [
          [
            -86.96456825888876,
            35.64130768526397
          ],
          [
            -86.96498213779387,
            35.64089343850271
          ],
          [
            -86.96523022687319,
            35.64130843902053
          ],
          [
            -86.96519800632085,
            35.64194704456146
          ],
          [
            -86.96544875923529,
            35.6422639558412
          ],
          [
            -86.96600536595983,
            35.64247502023776
          ],
          [
            -86.96623384555475,
            35.64278292184167
          ],
          [
            -86.96550504936229,
            35.64271432535318
          ],
          [
            -86.96540612806419,
            35.64271840116659
          ],
          [
            -86.9650927068353,
            35.64259124631667
          ],
          [
            -86.96497755275975,
            35.64254327088103
          ],
          [
            -86.9648142788807,
            35.64227110789817
          ],
          [
            -86.96448958273022,
            35.64167591896624
          ],
          [
            -86.96453878244029,
            35.64137684565438
          ],
          [
            -86.96456825888876,
            35.64130768526397
          ]
        ]
      ]
    },
    "outNow": 28
  },
  {
    "outageRecId": "2021-09-11-0225",
    "points": {
      "type": "Polygon",
      "coordinates": [
        [
          [
            -86.96666672465152,
            35.63845883673015
          ],
          [
            -86.96694971642937,
            35.63841677459699
          ],
          [
            -86.9676623586061,
            35.63850965028854
          ],
          [
            -86.96773640030813,
            35.63852085619307
          ],
          [
            -86.9672445880414,
            35.63886617656955
          ],
          [
            -86.96699713821268,
            35.63937791170784
          ],
          [
            -86.96678024485163,
            35.63997391163361
          ],
          [
            -86.9666402976684,
            35.64021297079766
          ],
          [
            -86.9665591896345,
            35.64025074620406
          ],
          [
            -86.96631165158446,
            35.6402922115591
          ],
          [
            -86.96604567271794,
            35.63964970880264
          ],
          [
            -86.9661005707465,
            35.63959918377146
          ],
          [
            -86.96645499087248,
            35.63875915603106
          ],
          [
            -86.96657323905237,
            35.63850728826812
          ],
          [
            -86.96666672465152,
            35.63845883673015
          ]
        ]
      ]
    },
    "outNow": 30
  },
  {
    "outageRecId": "2021-09-11-0226",
    "points": {
      "type": "Polygon",
      "coordinates": [
        [
          [
            -86.97135573858499,
            35.61666123900245
          ],
          [
            -86.97268674879017,
            35.61861199892182
          ],
          [
            -86.9715911855263,
            35.62262337712731
          ],
          [
            -86.97101240840512,
            35.62416482654604
          ],
          [
            -86.97076098771585,
            35.62472407049666
          ],
          [
            -86.96935626309445,
            35.6292426216796
          ],
          [
            -86.97161288174175,
            35.63355205402133
          ],
          [
            -86.97231118905982,
            35.63431868381867
          ],
          [
            -86.97239360423798,
            35.63504266431564
          ],
          [
            -86.97180318637795,
            35.6351274721822
          ],
          [
            -86.96863050734851,
            35.63420473928673
          ],
          [
            -86.96829727383415,
            35.63406218216864
          ],
          [
            -86.96560336101795,
            35.63145811905778
          ],
          [
            -86.96572997674461,
            35.62842074769425
          ],
          [
            -86.96716101778274,
            35.62072836465628
          ],
          [
            -86.97135573858499,
            35.61666123900245
          ]
        ]
      ]
    },
    "outNow": 69
  },
  {
    "outageRecId": "2021-09-11-0227",
    "points": {
      "type": "Polygon",
      "coordinates": [
        [
          [
            -86.96514400304035,
            35.62855417550065
          ],
          [
            -86.96570509718315,
            35.62899848696349
          ],
          [
            -86.96555536998513,
            35.62964136661222
          ],
          [
            -86.96644969397073,
            35.63174889310824
          ],
          [
            -86.96889031166445,
            35.63172158582919
          ],
          [
            -86.9690139938319,
            35.63182576357025
          ],
          [
            -86.96954946152617,
            35.63268192311136
          ],
          [
            -86.96896376689247,
            35.63261162381367
          ],
          [
            -86.96774073977788,
            35.63228488042587
          ],
          [
            -86.96630646227472,
            35.63171898655077
          ],
          [
            -86.9649649235237,
            35.63126161052358
          ],
          [
            -86.9647116738655,
            35.63085547408542
          ],
          [
            -86.96479485894083,
            35.62982640079258
          ],
          [
            -86.96486248819697,
            35.62920026609853
          ],
          [
            -86.96501777450604,
            35.62862447137
          ],
          [
            -86.96514400304035,
            35.62855417550065
          ]
        ]
      ]
    },
    "outNow": 28
  },
  {
    "outageRecId": "2021-09-11-0228",
    "points": {},
    "outNow": 1
  },
  {
    "outageRecId": "2021-09-11-0229",
    "points": {},
    "outNow": 1
  },
  {
    "outageRecId": "2021-09-11-0230",
    "points": {},
    "outNow": 1
  },
  {
    "outageRecId": "2021-09-11-0231",
    "points": {},
    "outNow": 1
  },
  {
    "outageRecId": "2021-09-11-0232",
    "points": {},
    "outNow": 1
  },
  {
    "outageRecId": "2021-09-11-0233",
    "points": {},
    "outNow": 1
  },
  {
    "outageRecId": "2021-09-11-0234",
    "points": {
      "type": "Polygon",
      "coordinates": [
        [
          [
            -86.96328252631577,
            35.63660922503918
          ],
          [
            -86.96414989292214,
            35.63660423275851
          ],
          [
            -86.96410616305545,
            35.63801992836499
          ],
          [
            -86.9643981035487,
            35.63865396485893
          ],
          [
            -86.96446009310637,
            35.63893699630794
          ],
          [
            -86.9644965649342,
            35.63931912785638
          ],
          [
            -86.96406404523228,
            35.63931957206395
          ],
          [
            -86.96370857055052,
            35.63889469219081
          ],
          [
            -86.96347451009781,
            35.63823294134941
          ],
          [
            -86.96328252631577,
            35.63660922503918
          ]
        ]
      ]
    },
    "outNow": 18
  },
  {
    "outageRecId": "2021-09-11-0235",
    "points": {},
    "outNow": 1
  },
  {
    "outageRecId": "2021-09-11-0236",
    "points": {},
    "outNow": 1
  },
  {
    "outageRecId": "2021-09-11-0237",
    "points": {},
    "outNow": 1
  },
  {
    "outageRecId": "2021-09-11-0238",
    "points": {},
    "outNow": 1
  },
  {
    "outageRecId": "2021-09-11-0239",
    "points": {
      "type": "Polygon",
      "coordinates": [
        [
          [
            -87.02425285062648,
            35.6122927952142
          ],
          [
            -87.02428289832137,
            35.61229476657909
          ],
          [
            -87.02432116210042,
            35.61229889729216
          ],
          [
            -87.02429387212818,
            35.61229913053948
          ],
          [
            -87.0242911429587,
            35.61229915386536
          ],
          [
            -87.02425560835039,
            35.6122949998177
          ],
          [
            -87.0242255606561,
            35.61229302844599
          ],
          [
            -87.02423647733326,
            35.61229293514813
          ],
          [
            -87.02424739314917,
            35.61229284185665
          ],
          [
            -87.02425285062648,
            35.6122927952142
          ]
        ]
      ]
    },
    "outNow": 17
  },
  {
    "outageRecId": "2021-09-11-0240",
    "points": {},
    "outNow": 1
  },
  {
    "outageRecId": "2021-09-11-0241",
    "points": {},
    "outNow": 1
  },
  {
    "outageRecId": "2021-09-11-0242",
    "points": {
      "type": "Polygon",
      "coordinates": [
        [
          [
            -86.97486902559002,
            35.60712287749391
          ],
          [
            -86.97563433732971,
            35.605900903175
          ],
          [
            -86.97762592792837,
            35.60338738770528
          ],
          [
            -86.98165802514312,
            35.6034787844824
          ],
          [
            -86.97892597041178,
            35.60522730623909
          ],
          [
            -86.97994703404217,
            35.60805288577076
          ],
          [
            -86.98001045459806,
            35.60827903486609
          ],
          [
            -86.97722078967696,
            35.60976935629212
          ],
          [
            -86.9766660376871,
            35.60996821543958
          ],
          [
            -86.97538108009626,
            35.60967854318893
          ],
          [
            -86.9753004795698,
            35.60940807749464
          ],
          [
            -86.97489190551319,
            35.6075030413853
          ],
          [
            -86.97486902559002,
            35.60712287749391
          ]
        ]
      ]
    },
    "outNow": 18
  },
  {
    "outageRecId": "2021-09-11-0243",
    "points": {
      "type": "Polygon",
      "coordinates": [
        [
          [
            -86.9506774277211,
            35.60030989792862
          ],
          [
            -86.9540453125724,
            35.59869316914437
          ],
          [
            -86.95507471962539,
            35.59985683902369
          ],
          [
            -86.95583343008867,
            35.60368755682667
          ],
          [
            -86.95850912759231,
            35.60634788969674
          ],
          [
            -86.96283207277506,
            35.60867650331558
          ],
          [
            -86.96335417789354,
            35.60942622945224
          ],
          [
            -86.95780577919784,
            35.60905933917504
          ],
          [
            -86.9538348596059,
            35.60729845958793
          ],
          [
            -86.95039172482679,
            35.60809023496005
          ],
          [
            -86.94707859319794,
            35.60838348166636
          ],
          [
            -86.94716655292434,
            35.60795772903381
          ],
          [
            -86.94634763380166,
            35.60146306875495
          ],
          [
            -86.9506774277211,
            35.60030989792862
          ]
        ]
      ]
    },
    "outNow": 44
  },
  {
    "outageRecId": "2021-09-11-0244",
    "points": {},
    "outNow": 1
  },
  {
    "outageRecId": "2021-09-11-0245",
    "points": {},
    "outNow": 1
  },
  {
    "outageRecId": "2021-09-11-0246",
    "points": {},
    "outNow": 1
  },
  {
    "outageRecId": "2021-09-11-0247",
    "points": {},
    "outNow": 1
  },
  {
    "outageRecId": "2021-09-11-0248",
    "points": {},
    "outNow": 1
  },
  {
    "outageRecId": "2021-09-11-0249",
    "points": {},
    "outNow": 1
  },
  {
    "outageRecId": "2021-09-11-0250",
    "points": {
      "type": "Polygon",
      "coordinates": [
        [
          [
            -87.04962406226352,
            35.61432142278389
          ],
          [
            -87.05004498719246,
            35.61435921710303
          ],
          [
            -87.05030718477725,
            35.61472959152793
          ],
          [
            -87.04974839044131,
            35.6145937294856
          ],
          [
            -87.04962406226352,
            35.61432142278389
          ]
        ]
      ]
    },
    "outNow": 7
  },
  {
    "outageRecId": "2021-09-11-0251",
    "points": {},
    "outNow": 1
  },
  {
    "outageRecId": "2021-09-11-0252",
    "points": {},
    "outNow": 1
  },
  {
    "outageRecId": "2021-09-11-0253",
    "points": {},
    "outNow": 1
  },
  {
    "outageRecId": "2021-09-11-0254",
    "points": {},
    "outNow": 1
  },
  {
    "outageRecId": "2021-09-11-0255",
    "points": {},
    "outNow": 1
  },
  {
    "outageRecId": "2021-09-11-0256",
    "points": {},
    "outNow": 1
  },
  {
    "outageRecId": "2021-09-11-0257",
    "points": {},
    "outNow": 1
  },
  {
    "outageRecId": "2021-09-11-0258",
    "points": {},
    "outNow": 1
  },
  {
    "outageRecId": "2021-09-11-0259",
    "points": {},
    "outNow": 1
  },
  {
    "outageRecId": "2021-09-11-0260",
    "points": {},
    "outNow": 1
  },
  {
    "outageRecId": "2021-09-11-0261",
    "points": {},
    "outNow": 1
  },
  {
    "outageRecId": "2021-09-11-0262",
    "points": {},
    "outNow": 1
  },
  {
    "outageRecId": "2021-09-11-0263",
    "points": {},
    "outNow": 1
  }
]
