[
  {
    "outageRecId": "2021-12-02-0005",
    "points": {
      "type": "Polygon",
      "coordinates": [
        [
          [
            -87.03868712428515,
            35.63559609448757
          ],
          [
            -87.03884146016838,
            35.63566052194899
          ],
          [
            -87.03885014353116,
            35.63567262708615
          ],
          [
            -87.03911908365778,
            35.63602875175982
          ],
          [
            -87.03912345932449,
            35.63603741410646
          ],
          [
            -87.03868712428515,
            35.63559609448757
          ]
        ]
      ]
    },
    "outNow": 5
  }
]
