[
  {
    "outageRecId": "2021-06-06-0063",
    "points": {
      "type": "Polygon",
      "coordinates": [
        [
          [
            -86.9914984635326,
            35.68470326745374
          ],
          [
            -86.99165235970499,
            35.68473844850674
          ],
          [
            -86.99131390427016,
            35.68519600304053
          ],
          [
            -86.99107730225423,
            35.68523436540854
          ],
          [
            -86.99096201388616,
            35.68506394574333
          ],
          [
            -86.9914984635326,
            35.68470326745374
          ]
        ]
      ]
    },
    "outNow": 5
  }
]
